{"sections":{"main":{"type":"main-page","disabled":true,"settings":{"page_full_width":false,"page_full_width_spacing":false,"padding_top":100,"padding_bottom":40}},"df17f504-26df-4cdc-b6df-52b2c6c01968":{"type":"newsletter","blocks":{"template--16928175325416__df17f504-26df-4cdc-b6df-52b2c6c01968-paragraph-1":{"type":"paragraph","settings":{"text":"<p>STAY UPTO DATE<\/p>","text_style":"subtitle"}},"template--16928175325416__df17f504-26df-4cdc-b6df-52b2c6c01968-heading-1":{"type":"heading","settings":{"heading":"Subscribe To Our Newsletter","heading_size":"h1"}},"template--16928175325416__df17f504-26df-4cdc-b6df-52b2c6c01968-email_form-1":{"type":"email_form","settings":{}}},"block_order":["template--16928175325416__df17f504-26df-4cdc-b6df-52b2c6c01968-paragraph-1","template--16928175325416__df17f504-26df-4cdc-b6df-52b2c6c01968-heading-1","template--16928175325416__df17f504-26df-4cdc-b6df-52b2c6c01968-email_form-1"],"settings":{"page_full_width":false,"page_full_width_spacing":false,"color_scheme":"background-1","padding_top":40,"padding_bottom":52,"custom_class_name":"home-2-news"}},"553abf25-cfbe-4ff8-8e47-e77e5a6aa775":{"type":"brand-logos","blocks":{"template--16928175325416__553abf25-cfbe-4ff8-8e47-e77e5a6aa775-column-1":{"type":"column","settings":{"image":"shopify:\/\/shop_images\/brand-h2-1-1x.png","link":"#"}},"fdf0fffc-5f8c-4be3-99be-a1b637953acc":{"type":"column","settings":{"image":"shopify:\/\/shop_images\/brand-h2-2-1x.png","link":"#"}},"db5da507-7933-409c-a9a4-5de64dc3a9f0":{"type":"column","settings":{"image":"shopify:\/\/shop_images\/brand-h2-3-1x.png","link":"#"}},"245271a4-10d7-4e10-af89-19db0ba1b4af":{"type":"column","settings":{"image":"shopify:\/\/shop_images\/brand-h2-4-1x.png","link":"#"}},"1fe59c92-9040-483b-9e32-99b605239793":{"type":"column","settings":{"image":"shopify:\/\/shop_images\/brand-h2-5-1x.png","link":"#"}},"c66d1ecf-7a76-4f0b-bd1b-27a386ccf92c":{"type":"column","settings":{"image":"shopify:\/\/shop_images\/brand-h2-6-1x.png","link":"#"}},"1ee2bbdd-ee46-4302-b137-3d4c741ec393":{"type":"column","settings":{"image":"shopify:\/\/shop_images\/brand-h2-7-1x.png","link":"#"}}},"block_order":["template--16928175325416__553abf25-cfbe-4ff8-8e47-e77e5a6aa775-column-1","fdf0fffc-5f8c-4be3-99be-a1b637953acc","db5da507-7933-409c-a9a4-5de64dc3a9f0","245271a4-10d7-4e10-af89-19db0ba1b4af","1fe59c92-9040-483b-9e32-99b605239793","c66d1ecf-7a76-4f0b-bd1b-27a386ccf92c","1ee2bbdd-ee46-4302-b137-3d4c741ec393"],"settings":{"page_full_width":true,"page_full_width_spacing":false,"title":"","heading_size":"h1","sub_heading":"","description":"","button_label":"","button_link":"","button_style_secondary":false,"column_alignment":"center","columns_desktop":6,"background_style":"primary","color_scheme":"accent-1","block_color_scheme":"accent-1","padding_top":40,"padding_bottom":40,"custom_class_name":"home-1-brands","swiper_enable":true,"desktop_column":7,"tablet_column":4,"mobile_column":2,"swiper_pagination":false,"swiper_navigation":false,"centered_slide":false,"auto_play":0,"swipe_on_mobile":false,"arrow_on_mobile":false,"columns_mobile":"1"}},"311a8b73-b34c-40cc-afd6-6e5ff2773499":{"type":"instagram-gallery","blocks":{"template--16928175325416__311a8b73-b34c-40cc-afd6-6e5ff2773499-text-1":{"type":"text","settings":{"block_image":"shopify:\/\/shop_images\/insta-1-2x.jpg","show_content":false,"icon_class":true,"block_sub_title":"Sub title","block_description":"Short description","block_button_link":"#"}},"3fb2743c-81fd-482e-b767-8f3ae3aa7478":{"type":"text","settings":{"block_image":"shopify:\/\/shop_images\/insta-2-2x.jpg","show_content":false,"icon_class":true,"block_sub_title":"Sub title","block_description":"Short description","block_button_link":"#"}},"5adc8e4b-9073-4c9e-9758-252ef6df0839":{"type":"text","settings":{"block_image":"shopify:\/\/shop_images\/insta-3-2x.jpg","show_content":false,"icon_class":true,"block_sub_title":"Sub title","block_description":"Short description","block_button_link":"#"}},"0207a74e-36c6-4969-b9f9-115a1be36ed7":{"type":"text","settings":{"block_image":"shopify:\/\/shop_images\/insta-4-2x.jpg","show_content":false,"icon_class":true,"block_sub_title":"Sub title","block_description":"Short description","block_button_link":"#"}},"a35d9edc-fff2-4c03-98a1-82a71145b00c":{"type":"text","settings":{"block_image":"shopify:\/\/shop_images\/insta-5-2x.jpg","show_content":false,"icon_class":true,"block_sub_title":"Sub title","block_description":"Short description","block_button_link":"#"}},"c58376eb-65ab-45ed-99f7-65aede99e953":{"type":"text","settings":{"block_image":"shopify:\/\/shop_images\/insta-6-2x.jpg","show_content":false,"icon_class":true,"block_sub_title":"Sub title","block_description":"Short description","block_button_link":"#"}}},"block_order":["template--16928175325416__311a8b73-b34c-40cc-afd6-6e5ff2773499-text-1","3fb2743c-81fd-482e-b767-8f3ae3aa7478","5adc8e4b-9073-4c9e-9758-252ef6df0839","0207a74e-36c6-4969-b9f9-115a1be36ed7","a35d9edc-fff2-4c03-98a1-82a71145b00c","c58376eb-65ab-45ed-99f7-65aede99e953"],"settings":{"page_full_width":true,"page_full_width_spacing":false,"title":"Instagram Views","heading_size":"h1","sub_heading":"Follow Us @birch.home","description":"","column_alignment":"center","button_label":"","button_link":"","color_scheme":"background-1","overlay_height":300,"overlay_height_laptop":250,"overlay_height_tab":300,"overlay_height_mobile":200,"desktop_content_alignment":"center","column_gap":"14","padding_top":100,"padding_bottom":0,"swiper_enable":true,"desktop_column":6,"laptop_column":4,"tablet_column":3,"mobile_column":2,"centered_slide":false,"swiper_pagination":true,"swiper_navigation":false,"auto_play":0,"swipe_on_mobile":false,"arrow_on_mobile":false,"custom_class_name":"home-1-insta"}},"986be370-df42-44d6-ae66-d21bb4bd9ca7":{"type":"instagram-gallery","blocks":{"77d3e54a-dfc3-40bd-a655-edc84023b166":{"type":"text","settings":{"block_image":"shopify:\/\/shop_images\/insta-2-1-2x.jpg","show_content":false,"icon_class":true,"block_sub_title":"Sub title","block_description":"Short description","block_button_link":"#"}},"b187f554-f52e-4575-bc72-dd66ff6a834c":{"type":"text","settings":{"block_image":"shopify:\/\/shop_images\/insta-2-2-2x.jpg","show_content":false,"icon_class":true,"block_sub_title":"Sub title","block_description":"Short description","block_button_link":"#"}},"bf5bee8e-3cad-41b0-8217-08c560a210c2":{"type":"text","settings":{"block_image":"shopify:\/\/shop_images\/insta-2-3-2x.jpg","show_content":false,"icon_class":true,"block_sub_title":"Sub title","block_description":"Short description","block_button_link":"#"}},"09480555-599e-4b16-9c9e-a5371112e112":{"type":"text","settings":{"block_image":"shopify:\/\/shop_images\/insta-2-4-2x.jpg","show_content":false,"icon_class":true,"block_sub_title":"Sub title","block_description":"Short description","block_button_link":"#"}},"55242c8b-28c2-4e58-82b8-bdf04c23399e":{"type":"text","settings":{"block_image":"shopify:\/\/shop_images\/insta-2-5-2x.jpg","show_content":false,"icon_class":true,"block_sub_title":"Sub title","block_description":"Short description","block_button_link":"#"}},"f0a401ec-4e52-4d3c-81b5-efc151accf31":{"type":"text","settings":{"block_image":"shopify:\/\/shop_images\/insta-2-6-2x.jpg","show_content":false,"icon_class":true,"block_sub_title":"Sub title","block_description":"Short description","block_button_link":"#"}}},"block_order":["77d3e54a-dfc3-40bd-a655-edc84023b166","b187f554-f52e-4575-bc72-dd66ff6a834c","bf5bee8e-3cad-41b0-8217-08c560a210c2","09480555-599e-4b16-9c9e-a5371112e112","55242c8b-28c2-4e58-82b8-bdf04c23399e","f0a401ec-4e52-4d3c-81b5-efc151accf31"],"settings":{"page_full_width":true,"page_full_width_spacing":false,"title":"","heading_size":"h1","sub_heading":"","description":"","column_alignment":"center","button_label":"","button_link":"","color_scheme":"background-1","overlay_height":300,"overlay_height_laptop":250,"overlay_height_tab":300,"overlay_height_mobile":200,"desktop_content_alignment":"center","column_gap":"0","padding_top":100,"padding_bottom":0,"swiper_enable":true,"desktop_column":6,"laptop_column":4,"tablet_column":3,"mobile_column":2,"centered_slide":false,"swiper_pagination":true,"swiper_navigation":false,"auto_play":0,"swipe_on_mobile":false,"arrow_on_mobile":false,"custom_class_name":"home-2-insta"}},"f93c1efa-b198-44d2-a57e-08d43681c332":{"type":"grid-banner","blocks":{"template--16928175325416__f93c1efa-b198-44d2-a57e-08d43681c332-text-1":{"type":"text","settings":{"block_image":"shopify:\/\/shop_images\/grid-2-1-1.5x.jpg","show_content":true,"block_title":"Italy Linen","enable_title_link":false,"block_sub_title":"","block_description":"FABRIC CLOTHES","block_button_text":"SHOP ALL","block_button_link":"#","desktop_content_alignment":"center","desktop_content_position":"middle-center","reverse_column":false}},"92b2da26-0ac2-4e24-b7ab-cf890fb3d261":{"type":"text","settings":{"block_image":"shopify:\/\/shop_images\/grid-2-2-1.5x.jpg","show_content":true,"block_title":"Frence Linen","enable_title_link":false,"block_sub_title":"","block_description":"FABRIC CLOTHES","block_button_text":"SHOP ALL","block_button_link":"#","desktop_content_alignment":"center","desktop_content_position":"middle-center","reverse_column":false}},"523f6556-200a-4f33-9f56-53b3c1cf3474":{"type":"text","settings":{"block_image":"shopify:\/\/shop_images\/grid-2-3-1.5x.jpg","show_content":true,"block_title":"Camb Linen","enable_title_link":false,"block_sub_title":"","block_description":"FABRIC CLOTHES","block_button_text":"SHOP ALL","block_button_link":"#","desktop_content_alignment":"center","desktop_content_position":"middle-center","reverse_column":false}},"e4cbdaa9-b6f3-4f5d-89d4-14c9d3571a3a":{"type":"text","settings":{"block_image":"shopify:\/\/shop_images\/grid-2-4-1.5x.jpg","show_content":true,"block_title":"Mark Linen","enable_title_link":false,"block_sub_title":"","block_description":"FABRIC CLOTHES","block_button_text":"SHOP ALL","block_button_link":"#","desktop_content_alignment":"center","desktop_content_position":"middle-center","reverse_column":false}},"e76a992a-3613-4258-9f03-0fce1e923556":{"type":"text","settings":{"block_image":"shopify:\/\/shop_images\/grid-2-5-1.5x.jpg","show_content":true,"block_title":"Fire Linen","enable_title_link":false,"block_sub_title":"","block_description":"FABRIC CLOTHES","block_button_text":"SHOP ALL","block_button_link":"#","desktop_content_alignment":"center","desktop_content_position":"middle-center","reverse_column":false}},"f68ba1a2-1379-4f79-89a5-4a4188c81580":{"type":"text","settings":{"block_image":"shopify:\/\/shop_images\/grid-2-6-1.5x.jpg","show_content":true,"block_title":"Marish Linen","enable_title_link":false,"block_sub_title":"","block_description":"FABRIC CLOTHES","block_button_text":"SHOP ALL","block_button_link":"#","desktop_content_alignment":"center","desktop_content_position":"middle-center","reverse_column":false}},"517a8936-27d8-4dcc-853f-f40e63b2ce2b":{"type":"text","settings":{"block_image":"shopify:\/\/shop_images\/grid-2-7-1.5x.jpg","show_content":true,"block_title":"Perquee Linen","enable_title_link":false,"block_sub_title":"","block_description":"FABRIC CLOTHES","block_button_text":"SHOP ALL","block_button_link":"#","desktop_content_alignment":"center","desktop_content_position":"middle-center","reverse_column":false}},"07d50cfb-c5be-48df-b920-eca330cd236c":{"type":"text","settings":{"block_image":"shopify:\/\/shop_images\/grid-2-8-1.5x.jpg","show_content":true,"block_title":"Light Linen","enable_title_link":false,"block_sub_title":"","block_description":"FABRIC CLOTHES","block_button_text":"SHOP ALL","block_button_link":"#","desktop_content_alignment":"center","desktop_content_position":"middle-center","reverse_column":false}}},"block_order":["template--16928175325416__f93c1efa-b198-44d2-a57e-08d43681c332-text-1","92b2da26-0ac2-4e24-b7ab-cf890fb3d261","523f6556-200a-4f33-9f56-53b3c1cf3474","e4cbdaa9-b6f3-4f5d-89d4-14c9d3571a3a","e76a992a-3613-4258-9f03-0fce1e923556","f68ba1a2-1379-4f79-89a5-4a4188c81580","517a8936-27d8-4dcc-853f-f40e63b2ce2b","07d50cfb-c5be-48df-b920-eca330cd236c"],"settings":{"page_full_width":false,"page_full_width_spacing":false,"title":"Our Brands","heading_size":"h1","sub_heading":"SHOP BY","description":"","button_label":"","button_link":"","button_style_secondary":false,"column_alignment":"center","color_scheme":"accent-1","banner_style":"overlay","background_style":"primary","content_color_scheme":"inverse","grid-column":"4","column_gap":"36","overlay_height":450,"overlay_height_laptop":300,"overlay_height_tab":300,"overlay_height_mobile":250,"button_style_underline":true,"padding_top":120,"padding_bottom":120,"custom_class_name":"home-2-grid","swiper_enable":false,"desktop_column":4,"laptop_column":4,"tablet_column":3,"mobile_column":1,"centered_slide":false,"swiper_pagination":false,"swiper_navigation":false,"auto_play":0}},"ea26684f-1f97-47a0-aa4e-95c12f529134":{"type":"masonry-banner","blocks":{"template--16928175325416__ea26684f-1f97-47a0-aa4e-95c12f529134-text-1":{"type":"text","settings":{"show_image":false,"show_content":true,"block_title":"Iam Looking For Fashion","block_sub_title":"TOP CATEGORIES","block_description":"","block_button_text":"","block_button_link":"","block_text_align":"center","block_position":"center"}},"template--16928175325416__ea26684f-1f97-47a0-aa4e-95c12f529134-text-2":{"type":"text","settings":{"block_image":"shopify:\/\/shop_images\/masonry-h1-2-1.5x.jpg","show_image":true,"show_content":true,"block_title":"","block_sub_title":"","block_description":"","block_button_text":"ACCESSORIES","block_button_link":"#","block_text_align":"center","block_position":"bottom-center"}},"template--16928175325416__ea26684f-1f97-47a0-aa4e-95c12f529134-text-3":{"type":"text","settings":{"block_image":"shopify:\/\/shop_images\/masonry-h1-4-1.5x.png","show_image":true,"show_content":true,"block_title":"","block_sub_title":"","block_description":"","block_button_text":"SHOP BAGS","block_button_link":"#","block_text_align":"center","block_position":"bottom-center"}},"83b18ff3-7302-4431-8bed-cebb8e48750b":{"type":"text","settings":{"block_image":"shopify:\/\/shop_images\/masonry-h1-3-1.5x.jpg","show_image":true,"show_content":true,"block_title":"","block_sub_title":"","block_description":"","block_button_text":"SHOES","block_button_link":"#","block_text_align":"center","block_position":"bottom-center"}}},"block_order":["template--16928175325416__ea26684f-1f97-47a0-aa4e-95c12f529134-text-1","template--16928175325416__ea26684f-1f97-47a0-aa4e-95c12f529134-text-2","template--16928175325416__ea26684f-1f97-47a0-aa4e-95c12f529134-text-3","83b18ff3-7302-4431-8bed-cebb8e48750b"],"settings":{"page_full_width":false,"page_full_width_spacing":false,"color_scheme":"background-1","title":"","heading_size":"h1","sub_heading":"","description":"","button_label":"","button_link":"","button_style_secondary":false,"column_alignment":"center","primary_image":"shopify:\/\/shop_images\/masonry-h1-1-2x.jpg","primary_title":"","heading_size_main":"h1","primary_sub_title":"","primary_description":"","primary_button_text":"WOMEN TOP","primary_button_link":"#","primary_text_align":"left","primary_position":"bottom-center","main_banner_style":"overlay_style","additional_banner_style":"overlay_style","content_width":"32\/68","lap_content_width":"32\/68","content_color_scheme":"accent-1","block_style":"style-2","padding_top":100,"padding_bottom":100,"overlay_style_height":270,"overlay_style_height_laptop":270,"overlay_style_height_tab":250,"overlay_style_height_mobile":240,"custom_class_name":"home-1-masonry"}},"4da34177-0083-4cf9-8ae1-443f8629df01":{"type":"video","settings":{"page_full_width":true,"page_full_width_spacing":false,"title":"","heading_size":"h1","sub_heading":"","description":"","button_label":"","button_link":"","button_style_secondary":false,"column_alignment":"center","content_style":"overlay","block_image":"shopify:\/\/shop_images\/cover-h3-1x.png","enable_image_link":false,"block_video":"https:\/\/cdn.shopify.com\/videos\/c\/o\/v\/2a7142ee67a540319d23346b0a6b7018.mp4","video_icon_color":"#ffffff","color_scheme":"inverse","padding_top":36,"padding_bottom":36}},"6292a630-8d29-4b98-a64d-c5fd2d815c71":{"type":"video","settings":{"page_full_width":true,"page_full_width_spacing":false,"title":"Casual Fashion Wears","heading_size":"h0","sub_heading":"","description":"","button_label":"","button_link":"","button_style_secondary":false,"column_alignment":"left","content_style":"overlay","block_image":"shopify:\/\/shop_images\/cover-h5-1x.png","enable_image_link":false,"block_video":"https:\/\/cdn.shopify.com\/videos\/c\/o\/v\/fda9c3eb33384eafbfe598714d1fe43f.mp4","video_icon_color":"#000000","color_scheme":"background-1","padding_top":40,"padding_bottom":40}},"44c1225e-5289-42aa-9740-0dc94c13c2d1":{"type":"slideshow-with-tabs","blocks":{"template--16928175325416__44c1225e-5289-42aa-9740-0dc94c13c2d1-slide-1":{"type":"slide","settings":{"image":"shopify:\/\/shop_images\/carousel-h2-2x.jpg","product":"a-line-casual-gathered-dress"}},"template--16928175325416__44c1225e-5289-42aa-9740-0dc94c13c2d1-slide-2":{"type":"slide","settings":{"image":"shopify:\/\/shop_images\/slide-tab-h1-2x.jpg","product":"a-line-layered-party-dress"}}},"block_order":["template--16928175325416__44c1225e-5289-42aa-9740-0dc94c13c2d1-slide-1","template--16928175325416__44c1225e-5289-42aa-9740-0dc94c13c2d1-slide-2"],"settings":{"page_full_width":false,"page_full_width_spacing":false,"sub_heading":"","title":"","color_scheme":"inverse","slide_height":"adapt_image","auto_play":0,"content_reverse":false,"show_vendor":false,"show_new_tag":false,"custom_class_name":"","padding_top":120,"padding_bottom":120}},"fd496ac1-09b7-4d7f-8810-9302e1112696":{"type":"collection-slider","settings":{"page_full_width":false,"page_full_width_spacing":false,"title":"","heading_size":"h1","sub_heading":"","description":"","button_label":"","button_link":"","button_style_secondary":false,"column_alignment":"center","disable_featured_image":false,"image":"shopify:\/\/shop_images\/slide-tab-h1-2x.jpg","height":"adapt","desktop_image_width":"large","collection":"collection-1","products_to_show":2,"columns_desktop":2,"show_view_all":false,"view_all_style":"solid","color_scheme":"background-1","image_ratio":"adapt","show_secondary_image":false,"show_vendor":false,"show_new_tag":false,"show_rating":false,"swiper_enable":true,"desktop_column":2,"laptop_column":2,"tablet_column":2,"mobile_column":2,"centered_slide":false,"swiper_pagination":true,"swiper_navigation":true,"auto_play":0,"swipe_on_mobile":false,"arrow_on_mobile":false,"columns_mobile":"1","padding_top":120,"padding_bottom":120}},"4199e6a3-e791-4502-ae38-82aed90a5f2b":{"type":"shop-the-look","blocks":{"template--16928175325416__4199e6a3-e791-4502-ae38-82aed90a5f2b-quote-3":{"type":"quote","settings":{"product":"double-handle-shoulder-bag","top_position":30,"left_position":60,"text_position":"on-right"}},"b0c7021c-4c39-46b7-b59f-1cc5e3f39a7d":{"type":"quote","settings":{"product":"a-line-maxi-dress","top_position":60,"left_position":30,"text_position":"on-right"}}},"block_order":["template--16928175325416__4199e6a3-e791-4502-ae38-82aed90a5f2b-quote-3","b0c7021c-4c39-46b7-b59f-1cc5e3f39a7d"],"settings":{"page_full_width":false,"page_full_width_spacing":false,"spot_image":"shopify:\/\/shop_images\/hotspot-h3-1.5x.jpg","heading":"New Bags","heading_size":"h1","description":"There are many variations of passages of Lorem Ipsum available, but the majority have suffered alteration in some form, by injected humour.","button_label":"SHOP ALL COLLECTIONS","button_link":"shopify:\/\/collections","button_style_underline":true,"column_alignment":"right","image_ratio":"square","show_secondary_image":false,"show_vendor":false,"show_new_tag":false,"show_rating":false,"padding_top":120,"padding_bottom":120}},"1b537657-0c01-42eb-bdda-0cb87f0ce899":{"type":"slideshow-with-tab1","blocks":{"template--16928062931176__1b537657-0c01-42eb-bdda-0cb87f0ce899-slide-1":{"type":"slide","settings":{"title":"Light Fashion Wear","heading_size":"h1","button_label":"jeans","button_link":"shopify:\/\/collections\/all","button_label_1":"shirts","button_link_1":"shopify:\/\/collections\/all","image":"shopify:\/\/shop_images\/Group_133677.jpg","product":"a-line-layered-party-dress"}},"template--16928062931176__1b537657-0c01-42eb-bdda-0cb87f0ce899-slide-2":{"type":"slide","settings":{"title":"Light Fashion Wear","heading_size":"h1","button_label":"jeans","button_link":"shopify:\/\/collections","button_label_1":"shirts","button_link_1":"shopify:\/\/collections","image":"shopify:\/\/shop_images\/img_2.jpg","product":"a-line-casual-gathered-dress"}},"template--16928062931176__1b537657-0c01-42eb-bdda-0cb87f0ce899-slide-3":{"type":"slide","settings":{"title":"Light Fashion Wear","heading_size":"h1","button_label":"jeans","button_link":"shopify:\/\/collections","button_label_1":"shirts","button_link_1":"shopify:\/\/collections","image":"shopify:\/\/shop_images\/Frame_35.jpg","product":"casual-womens-t-shirt"}}},"block_order":["template--16928062931176__1b537657-0c01-42eb-bdda-0cb87f0ce899-slide-1","template--16928062931176__1b537657-0c01-42eb-bdda-0cb87f0ce899-slide-2","template--16928062931176__1b537657-0c01-42eb-bdda-0cb87f0ce899-slide-3"],"settings":{"page_full_width":true,"page_full_width_spacing":false,"slide_height":"adapt_image","content_reverse":false,"sub_heading":"","title":"","color_scheme":"background-1","show_vendor":true,"show_new_tag":false,"custom_class_name":"custom-slideshow-tabs","padding_top":45,"padding_bottom":45}},"748e5941-029c-43fa-87a1-e51e34b89113":{"type":"slideshow-with-tab1","blocks":{"template--16928062931176__748e5941-029c-43fa-87a1-e51e34b89113-slide-1":{"type":"slide","settings":{"title":"Dark Fashion Wear","heading_size":"h1","button_label":"Jerkin or Court","button_link":"shopify:\/\/collections","button_label_1":"Inner Wear","button_link_1":"shopify:\/\/collections","image":"shopify:\/\/shop_images\/img_2.jpg","product":"a-line-layered-party-dress"}},"template--16928062931176__748e5941-029c-43fa-87a1-e51e34b89113-slide-2":{"type":"slide","settings":{"title":"Dark Fashion Wear","heading_size":"h1","button_label":"Jerkin or Court","button_link":"","button_label_1":"Inner Wear","button_link_1":"shopify:\/\/collections\/accessories","image":"shopify:\/\/shop_images\/Group_133677.jpg","product":"casual-mens-shoe"}},"template--16928062931176__748e5941-029c-43fa-87a1-e51e34b89113-slide-3":{"type":"slide","settings":{"title":"Dark Fashion Wear","heading_size":"h1","button_label":"Jerkin or Court","button_link":"shopify:\/\/collections","button_label_1":"Inner Wear","button_link_1":"shopify:\/\/collections","image":"shopify:\/\/shop_images\/hotspot-h3-1.5x.jpg","product":"dinosaur-soft-toy"}}},"block_order":["template--16928062931176__748e5941-029c-43fa-87a1-e51e34b89113-slide-1","template--16928062931176__748e5941-029c-43fa-87a1-e51e34b89113-slide-2","template--16928062931176__748e5941-029c-43fa-87a1-e51e34b89113-slide-3"],"settings":{"page_full_width":true,"page_full_width_spacing":false,"slide_height":"adapt_image","content_reverse":true,"sub_heading":"","title":"","color_scheme":"background-1","show_vendor":true,"show_new_tag":false,"custom_class_name":"custom-slideshow-with-tabs","padding_top":45,"padding_bottom":45}}},"order":["main","df17f504-26df-4cdc-b6df-52b2c6c01968","553abf25-cfbe-4ff8-8e47-e77e5a6aa775","311a8b73-b34c-40cc-afd6-6e5ff2773499","986be370-df42-44d6-ae66-d21bb4bd9ca7","f93c1efa-b198-44d2-a57e-08d43681c332","ea26684f-1f97-47a0-aa4e-95c12f529134","4da34177-0083-4cf9-8ae1-443f8629df01","6292a630-8d29-4b98-a64d-c5fd2d815c71","44c1225e-5289-42aa-9740-0dc94c13c2d1","fd496ac1-09b7-4d7f-8810-9302e1112696","4199e6a3-e791-4502-ae38-82aed90a5f2b","1b537657-0c01-42eb-bdda-0cb87f0ce899","748e5941-029c-43fa-87a1-e51e34b89113"]}